freeproxydownloader/LICENSE
freeproxydownloader/README.MD
freeproxydownloader/__init__.py
freeproxydownloader/aaa_execute_requests_new.py
freeproxydownloader/ad_ping_check.py
freeproxydownloader/ad_proxy.py
freeproxydownloader/downloader_cpr.py
freeproxydownloader/requirements.txt
freeproxydownloader/thirdparty.json
freeproxydownloader-0.11.dist-info/LICENSE.rst
freeproxydownloader-0.11.dist-info/METADATA
freeproxydownloader-0.11.dist-info/WHEEL
freeproxydownloader-0.11.dist-info/top_level.txt
freeproxydownloader-0.11.dist-info/RECORD
