Metadata-Version: 2.1
Name: freeproxydownloader
Version: 0.11
Summary: Gets proxies from public lists and checks them (ping, hidden IP, http connection)
Home-page: https://github.com/hansalemaos/freeproxydownloader
Author: Johannes Fischer
Author-email: <aulasparticularesdealemaosp@gmail.com>
License: MIT
Keywords: proxy,proxies,windows,bot
Classifier: Development Status :: 4 - Beta
Classifier: Programming Language :: Python :: 3 :: Only
Classifier: Programming Language :: Python :: 3.9
Classifier: Topic :: Scientific/Engineering :: Visualization
Classifier: Topic :: Software Development :: Libraries :: Python Modules
Classifier: Topic :: Text Editors :: Text Processing
Classifier: Topic :: Text Processing :: General
Classifier: Topic :: Text Processing :: Indexing
Classifier: Topic :: Text Processing :: Filters
Classifier: Topic :: Utilities
License-File: LICENSE.rst
Requires-Dist: cprinter
Requires-Dist: fake-headers
Requires-Dist: flatten-everything
Requires-Dist: kthread
Requires-Dist: numpy
Requires-Dist: pandas
Requires-Dist: PrettyColorPrinter
Requires-Dist: regex
Requires-Dist: requests
Requires-Dist: ujson
